{
  "year": 2015,
  "states": [
    {
      "state": "Alabama",
      "house_women": 16,
      "senate_women": 4,
      "total_women": 20,
      "total_seats": 140,
      "percentage_women": "14.3%"
    },
    {
      "state": "Alaska",
      "house_women": 12,
      "senate_women": 5,
      "total_women": 17,
      "total_seats": 60,
      "percentage_women": "28.3%"
    },
    {
      "state": "Arizona",
      "house_women": 19,
      "senate_women": 13,
      "total_women": 32,
      "total_seats": 90,
      "percentage_women": "35.6%"
    },
    {
      "state": "Arkansas",
      "house_women": 20,
      "senate_women": 7,
      "total_women": 27,
      "total_seats": 135,
      "percentage_women": "20.0%"
    },
    {
      "state": "California",
      "house_women": 19,
      "senate_women": 12,
      "total_women": 31,
      "total_seats": 120,
      "percentage_women": "25.8%"
    },
    {
      "state": "Colorado",
      "house_women": 30,
      "senate_women": 12,
      "total_women": 42,
      "total_seats": 100,
      "percentage_women": "42.0%"
    },
    {
      "state": "Connecticut",
      "house_women": 44,
      "senate_women": 9,
      "total_women": 53,
      "total_seats": 187,
      "percentage_women": "28.3%"
    },
    {
      "state": "Delaware",
      "house_women": 9,
      "senate_women": 6,
      "total_women": 15,
      "total_seats": 62,
      "percentage_women": "24.2%"
    },
    {
      "state": "Florida",
      "house_women": 28,
      "senate_women": 12,
      "total_women": 40,
      "total_seats": 160,
      "percentage_women": "25.0%"
    },
    {
      "state": "Georgia",
      "house_women": 47,
      "senate_women": 9,
      "total_women": 56,
      "total_seats": 236,
      "percentage_women": "23.7%"
    },
    {
      "state": "Hawaii",
      "house_women": 14,
      "senate_women": 8,
      "total_women": 22,
      "total_seats": 76,
      "percentage_women": "28.9%"
    },
    {
      "state": "Idaho",
      "house_women": 19,
      "senate_women": 10,
      "total_women": 29,
      "total_seats": 105,
      "percentage_women": "27.6%"
    },
    {
      "state": "Illinois",
      "house_women": 41,
      "senate_women": 14,
      "total_women": 55,
      "total_seats": 177,
      "percentage_women": "31.1%"
    },
    {
      "state": "Indiana",
      "house_women": 22,
      "senate_women": 9,
      "total_women": 31,
      "total_seats": 150,
      "percentage_women": "20.7%"
    },
    {
      "state": "Iowa",
      "house_women": 27,
      "senate_women": 7,
      "total_women": 34,
      "total_seats": 150,
      "percentage_women": "22.7%"
    },
    {
      "state": "Kansas",
      "house_women": 28,
      "senate_women": 13,
      "total_women": 41,
      "total_seats": 165,
      "percentage_women": "24.8%"
    },
    {
      "state": "Kentucky",
      "house_women": 19,
      "senate_women": 4,
      "total_women": 23,
      "total_seats": 138,
      "percentage_women": "16.7%"
    },
    {
      "state": "Louisiana",
      "house_women": 13,
      "senate_women": 4,
      "total_women": 17,
      "total_seats": 144,
      "percentage_women": "11.8%"
    },
    {
      "state": "Maine",
      "house_women": 46,
      "senate_women": 8,
      "total_women": 54,
      "total_seats": 186,
      "percentage_women": "29.0%"
    },
    {
      "state": "Maryland",
      "house_women": 46,
      "senate_women": 13,
      "total_women": 59,
      "total_seats": 188,
      "percentage_women": "31.4%"
    },
    {
      "state": "Massachusetts",
      "house_women": 39,
      "senate_women": 12,
      "total_women": 51,
      "total_seats": 200,
      "percentage_women": "25.5%"
    },
    {
      "state": "Michigan",
      "house_women": 27,
      "senate_women": 4,
      "total_women": 31,
      "total_seats": 148,
      "percentage_women": "20.9%"
    },
    {
      "state": "Minnesota",
      "house_women": 44,
      "senate_women": 23,
      "total_women": 67,
      "total_seats": 201,
      "percentage_women": "33.3%"
    },
    {
      "state": "Mississippi",
      "house_women": 22,
      "senate_women": 8,
      "total_women": 30,
      "total_seats": 174,
      "percentage_women": "17.2%"
    },
    {
      "state": "Missouri",
      "house_women": 43,
      "senate_women": 6,
      "total_women": 49,
      "total_seats": 197,
      "percentage_women": "24.9%"
    },
    {
      "state": "Montana",
      "house_women": 29,
      "senate_women": 18,
      "total_women": 47,
      "total_seats": 150,
      "percentage_women": "31.3%"
    },
    {
      "state": "Nebraska",
      "house_women": 0,
      "senate_women": 11,
      "total_women": 11,
      "total_seats": 49,
      "percentage_women": "22.4%"
    },
    {
      "state": "Nevada",
      "house_women": 16,
      "senate_women": 5,
      "total_women": 21,
      "total_seats": 63,
      "percentage_women": "33.3%"
    },
    {
      "state": "New Hampshire",
      "house_women": 115,
      "senate_women": 8,
      "total_women": 123,
      "total_seats": 424,
      "percentage_women": "29.0%"
    },
    {
      "state": "New Jersey",
      "house_women": 25,
      "senate_women": 11,
      "total_women": 36,
      "total_seats": 120,
      "percentage_women": "30.0%"
    },
    {
      "state": "New Mexico",
      "house_women": 23,
      "senate_women": 7,
      "total_women": 30,
      "total_seats": 112,
      "percentage_women": "26.8%"
    },
    {
      "state": "New York",
      "house_women": 41,
      "senate_women": 11,
      "total_women": 52,
      "total_seats": 213,
      "percentage_women": "24.4%"
    },
    {
      "state": "North Carolina",
      "house_women": 26,
      "senate_women": 12,
      "total_women": 38,
      "total_seats": 170,
      "percentage_women": "22.4%"
    },
    {
      "state": "North Dakota",
      "house_women": 19,
      "senate_women": 8,
      "total_women": 27,
      "total_seats": 141,
      "percentage_women": "19.1%"
    },
    {
      "state": "Ohio",
      "house_women": 26,
      "senate_women": 7,
      "total_women": 33,
      "total_seats": 132,
      "percentage_women": "25.0%"
    },
    {
      "state": "Oklahoma",
      "house_women": 14,
      "senate_women": 6,
      "total_women": 20,
      "total_seats": 149,
      "percentage_women": "13.4%"
    },
    {
      "state": "Oregon",
      "house_women": 20,
      "senate_women": 8,
      "total_women": 28,
      "total_seats": 90,
      "percentage_women": "31.1%"
    },
    {
      "state": "Pennsylvania",
      "house_women": 37,
      "senate_women": 9,
      "total_women": 46,
      "total_seats": 253,
      "percentage_women": "18.2%"
    },
    {
      "state": "Rhode Island",
      "house_women": 21,
      "senate_women": 10,
      "total_women": 31,
      "total_seats": 113,
      "percentage_women": "27.4%"
    },
    {
      "state": "South Carolina",
      "house_women": 22,
      "senate_women": 1,
      "total_women": 23,
      "total_seats": 170,
      "percentage_women": "13.5%"
    },
    {
      "state": "South Dakota",
      "house_women": 15,
      "senate_women": 7,
      "total_women": 22,
      "total_seats": 105,
      "percentage_women": "21.0%"
    },
    {
      "state": "Tennessee",
      "house_women": 17,
      "senate_women": 6,
      "total_women": 23,
      "total_seats": 132,
      "percentage_women": "17.4%"
    },
    {
      "state": "Texas",
      "house_women": 29,
      "senate_women": 7,
      "total_women": 36,
      "total_seats": 181,
      "percentage_women": "19.9%"
    },
    {
      "state": "Utah",
      "house_women": 10,
      "senate_women": 6,
      "total_women": 16,
      "total_seats": 104,
      "percentage_women": "15.4%"
    },
    {
      "state": "Vermont",
      "house_women": 64,
      "senate_women": 9,
      "total_women": 73,
      "total_seats": 180,
      "percentage_women": "40.6%"
    },
    {
      "state": "Virginia",
      "house_women": 16,
      "senate_women": 8,
      "total_women": 24,
      "total_seats": 140,
      "percentage_women": "17.1%"
    },
    {
      "state": "Washington",
      "house_women": 31,
      "senate_women": 18,
      "total_women": 49,
      "total_seats": 147,
      "percentage_women": "33.3%"
    },
    {
      "state": "West Virginia",
      "house_women": 19,
      "senate_women": 1,
      "total_women": 20,
      "total_seats": 134,
      "percentage_women": "14.9%"
    },
    {
      "state": "Wisconsin",
      "house_women": 22,
      "senate_women": 11,
      "total_women": 33,
      "total_seats": 132,
      "percentage_women": "25.0%"
    },
    {
      "state": "Wyoming",
      "house_women": 11,
      "senate_women": 1,
      "total_women": 12,
      "total_seats": 90,
      "percentage_women": "13.3%"
    }
  ]
}